JiyuTransformersDeZiranyuyanChuliNlpRumenFix1/README.md
JiyuTransformersDeZiranyuyanChuliNlpRumenFix1/__init__.py
JiyuTransformersDeZiranyuyanChuliNlpRumenFix1/__main__.py
JiyuTransformersDeZiranyuyanChuliNlpRumenFix1/file.epub
JiyuTransformersDeZiranyuyanChuliNlpRumenFix1/index.html
JiyuTransformersDeZiranyuyanChuliNlpRumenFix1/css/__init__.py
JiyuTransformersDeZiranyuyanChuliNlpRumenFix1/css/annotations.css
JiyuTransformersDeZiranyuyanChuliNlpRumenFix1/css/main.css
JiyuTransformersDeZiranyuyanChuliNlpRumenFix1/css/normalize.css
JiyuTransformersDeZiranyuyanChuliNlpRumenFix1/css/popup.css
JiyuTransformersDeZiranyuyanChuliNlpRumenFix1/font/__init__.py
JiyuTransformersDeZiranyuyanChuliNlpRumenFix1/font/fontello.eot
JiyuTransformersDeZiranyuyanChuliNlpRumenFix1/font/fontello.svg
JiyuTransformersDeZiranyuyanChuliNlpRumenFix1/font/fontello.ttf
JiyuTransformersDeZiranyuyanChuliNlpRumenFix1/font/fontello.woff
JiyuTransformersDeZiranyuyanChuliNlpRumenFix1/img/__init__.py
JiyuTransformersDeZiranyuyanChuliNlpRumenFix1/img/annotator-glyph-sprite.png
JiyuTransformersDeZiranyuyanChuliNlpRumenFix1/img/annotator-icon-sprite.png
JiyuTransformersDeZiranyuyanChuliNlpRumenFix1/img/apple-touch-icon.png
JiyuTransformersDeZiranyuyanChuliNlpRumenFix1/img/cancelfullscreen.png
JiyuTransformersDeZiranyuyanChuliNlpRumenFix1/img/close.png
JiyuTransformersDeZiranyuyanChuliNlpRumenFix1/img/fullscreen.png
JiyuTransformersDeZiranyuyanChuliNlpRumenFix1/img/loader.gif
JiyuTransformersDeZiranyuyanChuliNlpRumenFix1/img/menu-icon.png
JiyuTransformersDeZiranyuyanChuliNlpRumenFix1/img/save.png
JiyuTransformersDeZiranyuyanChuliNlpRumenFix1/img/saved.png
JiyuTransformersDeZiranyuyanChuliNlpRumenFix1/img/settings-s.png
JiyuTransformersDeZiranyuyanChuliNlpRumenFix1/img/settings.png
JiyuTransformersDeZiranyuyanChuliNlpRumenFix1/img/star.png
JiyuTransformersDeZiranyuyanChuliNlpRumenFix1/js/__init__.py
JiyuTransformersDeZiranyuyanChuliNlpRumenFix1/js/epub.js
jiyu_transformers_de_ziranyuyan_chuli_nlp_rumen_fix1-2025.3.25.0.dist-info/METADATA
jiyu_transformers_de_ziranyuyan_chuli_nlp_rumen_fix1-2025.3.25.0.dist-info/WHEEL
jiyu_transformers_de_ziranyuyan_chuli_nlp_rumen_fix1-2025.3.25.0.dist-info/entry_points.txt
jiyu_transformers_de_ziranyuyan_chuli_nlp_rumen_fix1-2025.3.25.0.dist-info/top_level.txt
jiyu_transformers_de_ziranyuyan_chuli_nlp_rumen_fix1-2025.3.25.0.dist-info/RECORD
